[
  {
    "timestamp_utc": "2025-08-19T06:39:35.975480Z",
    "status": "success",
    "pages_checked": 26,
    "changes_found": 2,
    "errors": []
  },
  {
    "timestamp_utc": "2025-08-19T04:34:58.883960Z",
    "status": "success",
    "pages_checked": 26,
    "changes_found": 1,
    "errors": []
  },
  {
    "timestamp_utc": "2025-08-19T02:45:59.826851Z",
    "status": "success",
    "pages_checked": 26,
    "changes_found": 1,
    "errors": []
  },
  {
    "timestamp_utc": "2025-08-19T02:28:31.325608Z",
    "status": "success",
    "pages_checked": 26,
    "changes_found": 1,
    "errors": []
  },
  {
    "timestamp_utc": "2025-08-19T02:06:12.243333Z",
    "status": "success",
    "pages_checked": 26,
    "changes_found": 2,
    "errors": []
  },
  {
    "timestamp_utc": "2025-08-16T01:59:46.282045Z",
    "status": "success",
    "pages_checked": 20,
    "changes_found": 0,
    "errors": []
  },
  {
    "timestamp_utc": "2025-08-15T23:01:28.726219Z",
    "status": "success",
    "pages_checked": 20,
    "changes_found": 0,
    "errors": []
  },
  {
    "timestamp_utc": "2025-08-15T18:38:07.718304Z",
    "status": "success",
    "pages_checked": 20,
    "changes_found": 0,
    "errors": []
  },
  {
    "timestamp_utc": "2025-08-15T12:52:49.506561Z",
    "status": "success",
    "pages_checked": 20,
    "changes_found": 0,
    "errors": []
  },
  {
    "timestamp_utc": "2025-08-15T06:39:36.849893Z",
    "status": "success",
    "pages_checked": 20,
    "changes_found": 0,
    "errors": []
  },
  {
    "timestamp_utc": "2025-08-15T06:07:46.886483Z",
    "status": "success",
    "pages_checked": 20,
    "changes_found": 0,
    "errors": []
  },
  {
    "timestamp_utc": "2025-08-08T18:37:19.406120Z",
    "status": "success",
    "pages_checked": 20,
    "changes_found": 0,
    "errors": []
  },
  {
    "timestamp_utc": "2025-08-08T12:58:25.424266Z",
    "status": "success",
    "pages_checked": 20,
    "changes_found": 0,
    "errors": []
  },
  {
    "timestamp_utc": "2025-08-08T06:42:02.515377Z",
    "status": "success",
    "pages_checked": 20,
    "changes_found": 0,
    "errors": []
  },
  {
    "timestamp_utc": "2025-08-08T02:21:00.133284Z",
    "status": "success",
    "pages_checked": 20,
    "changes_found": 0,
    "errors": []
  },
  {
    "timestamp_utc": "2025-08-07T18:42:06.440635Z",
    "status": "success",
    "pages_checked": 20,
    "changes_found": 0,
    "errors": []
  },
  {
    "timestamp_utc": "2025-08-07T12:58:22.821022Z",
    "status": "success",
    "pages_checked": 20,
    "changes_found": 0,
    "errors": []
  },
  {
    "timestamp_utc": "2025-08-07T06:43:13.197627Z",
    "status": "success",
    "pages_checked": 20,
    "changes_found": 0,
    "errors": []
  },
  {
    "timestamp_utc": "2025-08-07T02:20:42.894100Z",
    "status": "success",
    "pages_checked": 20,
    "changes_found": 0,
    "errors": []
  },
  {
    "timestamp_utc": "2025-08-06T18:40:11.557236Z",
    "status": "success",
    "pages_checked": 20,
    "changes_found": 0,
    "errors": []
  },
  {
    "timestamp_utc": "2025-08-06T12:58:51.210368Z",
    "status": "success",
    "pages_checked": 20,
    "changes_found": 0,
    "errors": []
  },
  {
    "timestamp_utc": "2025-08-06T06:43:40.281861Z",
    "status": "success",
    "pages_checked": 20,
    "changes_found": 0,
    "errors": []
  },
  {
    "timestamp_utc": "2025-08-06T02:20:21.479641Z",
    "status": "success",
    "pages_checked": 20,
    "changes_found": 0,
    "errors": []
  },
  {
    "timestamp_utc": "2025-08-05T18:42:16.433423Z",
    "status": "success",
    "pages_checked": 20,
    "changes_found": 0,
    "errors": []
  },
  {
    "timestamp_utc": "2025-08-05T15:52:03.183937Z",
    "status": "success",
    "pages_checked": 20,
    "changes_found": 1,
    "errors": []
  }
]